src/__init__.py
src/generator.py
azkaban_helper-1.0.2.dist-info/LICENSE.txt
azkaban_helper-1.0.2.dist-info/METADATA
azkaban_helper-1.0.2.dist-info/WHEEL
azkaban_helper-1.0.2.dist-info/entry_points.txt
azkaban_helper-1.0.2.dist-info/top_level.txt
azkaban_helper-1.0.2.dist-info/RECORD
