Metadata-Version: 2.1
Name: azkaban-helper
Version: 1.0.2
Summary: Azkaban Flow Generator
Home-page: https://github.com/JingZhang-Cherish/azkaban_helper.git
Author: Jing Zhang
Author-email: cherish244612023@gmail.com
Maintainer: Jing Zhang
Maintainer-email: cherish244612023@gmail.com
License: MIT License
Project-URL: Documentation, https://github.com/JingZhang-Cherish/azkaban_helper/blob/master/README.md
Project-URL: Source, https://github.com/JingZhang-Cherish/azkaban_helper.git
Project-URL: PyPi, https://pypi.org/project/azkaban-helper/
Project-URL: Chinese Docs, https://github.com/JingZhang-Cherish/azkaban_helper/blob/master/README-zh.md
Keywords: azkaban config flows excel
Platform: Operating System :: MacOS :: MacOS X
Platform: Operating System :: Microsoft :: Windows
Platform: Operating System :: POSIX
Classifier: Development Status :: 4 - Beta
Classifier: Intended Audience :: Developers
Classifier: Environment :: Console
Classifier: Topic :: Software Development :: Build Tools
Classifier: License :: OSI Approved :: MIT License
Classifier: Programming Language :: Python :: 3 :: Only
Classifier: Programming Language :: Python :: 3.9
Requires-Python: >=3
Requires-Dist: requests (~=2.25.1)
Requires-Dist: xlrd (~=1.2.0)
Requires-Dist: PyYAML (~=5.4.1)
Requires-Dist: requests-toolbelt (~=0.9.1)
